lotrsdk/__init__.py
lotrsdk/api/__init__.py
lotrsdk/api/api_client.py
lotrsdk/api/movies_api.py
lotrsdk/api/quotes_api.py
lotrsdk/entities/__init__.py
lotrsdk/entities/base_entity.py
lotrsdk/entities/collection.py
lotrsdk/entities/movie.py
lotrsdk/entities/quote.py
test/__init__.py
test/test_api_api_client.py
test/test_entities_base_entity.py
test/test_entities_collection.py
test/test_entities_movie.py
test/test_entities_quote.py
lotrsdkbybnelson0-1.0.0.dist-info/LICENSE
lotrsdkbybnelson0-1.0.0.dist-info/METADATA
lotrsdkbybnelson0-1.0.0.dist-info/WHEEL
lotrsdkbybnelson0-1.0.0.dist-info/top_level.txt
lotrsdkbybnelson0-1.0.0.dist-info/RECORD
